{"73": {"success": true, "google": {"ity": "bmp", "ou": "http://www.definicionabc.com/wp-content/uploads/etapa-litica.bmp", "rid": "psKa6z0stDi0PM", "th": 144, "itg": false, "oh": 180, "tw": 256, "pt": "Definici\u00f3n de Etapa L\u00edtica \u00bb Concepto en Definici\u00f3n ABC", "ow": 320, "isu": "definicionabc.com", "ru": "http://www.definicionabc.com/historia/etapa-litica.php", "tu": "https://encrypted-tbn1.gstatic.com/images?q=tbn:ANd9GcRCfBJfWdu9zLzaT_8vxIHp2nrivZhF136Rkd4wSaNLbczfkdAA", "s": "Definici\u00f3n de Etapa L\u00edtica", "id": "A7NBF8wBaszlaM:"}, "filename": "73.jpg?cb=1224268536", "image_link": "http://image.slidesharecdn.com/etapa-anal-2-1224293635233708-8/95/etapa-anal-2-2-728.jpg?cb=1224268536", "original_filename": "etapa-anal-2-2-728.jpg?cb=1224268536"}, "27": {"success": true, "google": {"isu": "malldelrio.com", "cb": 21, "ou": "http://www.malldelrio.com/wp-content/uploads/2015/04/l-etapa.jpg", "rid": "ldrXN9tmcbzpNM", "s": "", "ity": "jpg", "pt": "ETAPA | Mall del Rio", "itg": false, "cl": 6, "th": 225, "oh": 540, "sc": 1, "ow": 540, "cr": 6, "ru": "http://www.malldelrio.com/product/etapa/", "tu": "https://encrypted-tbn3.gstatic.com/images?q=tbn:ANd9GcR73M_l0setqYwye5sG1k9J5bkB7TnGV36HHZYOCEkysczY1yJgOw", "ct": 21, "tw": 225, "id": "Ah-XrQ02DmOX5M:"}, "filename": "27.jpg", "image_link": "http://www.urbecom.com/blog/wp-content/uploads/2009/07/etapas-del-plan-de-marketing-300x257.jpg", "original_filename": "etapas-del-plan-de-marketing-300x257.jpg"}, "84": {"success": true, "google": {"ity": "jpg", "cb": 3, "ou": "http://media.djmania.net/images/extra/Etapa_de_potencia_BHM_-_200_W_RMS__-_AMP-700.jpg", "rid": "06L9yjg9aMl_nM", "s": "Manual Etapa de potencia BHM - 200 W RMS - AMP-700.pdf", "sc": 1, "itg": false, "oh": 1215, "th": 121, "pt": "Etapa de potencia BHM - 200 W RMS - AMP-700 - DJMania", "ow": 4197, "isu": "djmania.es", "ru": "http://djmania.es/p/etapa-de-potencia-bhm-200-w-rms-amp-700", "tu": "https://encrypted-tbn1.gstatic.com/images?q=tbn:ANd9GcQQKNWBlVh8PpZC0pzh9LrQyUldA_USgm16Xu1XwCRacBBlsmLO", "ct": 6, "tw": 418, "id": "UNi1NcXSKo0LsM:"}, "filename": "84.jpg", "image_link": "http://www.marketingguerrilla.es/wp-content/uploads/2013/04/nueva_etapa.jpg", "original_filename": "nueva_etapa.jpg"}, "15": {"success": true, "google": {"cr": 3, "tw": 259, "cl": 3, "cb": 3, "th": 194}, "filename": "15.png", "image_link": "https://www.etapa.com.br/grupoetapa/assets//images/curso-etapa-logo.png", "original_filename": "curso-etapa-logo.png"}, "28": {"success": true, "google": {"ity": "jpg", "tw": 306, "ou": "https://gitanatropical.files.wordpress.com/2013/06/etapas-vida.jpg", "rid": "cVpSV5ljHWKmDM", "sc": 1, "itg": false, "oh": 359, "th": 164, "pt": "Los peligros de quemar etapas | Gitana tropical", "ow": 668, "isu": "gitanatropical.wordpress.com", "ru": "https://gitanatropical.wordpress.com/2013/06/12/los-peligros-de-quemar-etapas/", "tu": "https://encrypted-tbn3.gstatic.com/images?q=tbn:ANd9GcTp547hxOYIEtxxuQ4_Y0xy4ZmQheqpz5eC8YCc6_7d5CyVHJC0bw", "s": "Una frase muy com\u00fan en nuestros d\u00edas es la expresi\u00f3n \u201cquemar etapas\u201d, que generalmente se aplica a los ni\u00f1os y adolescentes cuando estos se adelantan a su ...", "id": "KpBjFucgCfWmUM:"}, "filename": "28.jpg", "image_link": "http://www.holamundo.mx/wp-content/uploads/2013/12/etapas.jpg", "original_filename": "etapas.jpg"}, "32": {"success": true, "google": {"ity": "jpg", "tw": 259, "ou": "https://camilomendoza.files.wordpress.com/2011/11/etapas3.jpg", "rid": "DZ3RLnc3w_9peM", "sc": 1, "itg": false, "oh": 345, "th": 194, "pt": "Adicciones | Prop\u00f3sitos", "ow": 460, "isu": "camilomendoza.wordpress.com", "ru": "https://camilomendoza.wordpress.com/adicciones-2/", "tu": "https://encrypted-tbn0.gstatic.com/images?q=tbn:ANd9GcQ40oVANZWi-p2XMZuF8-ZmOxgyW94WGv4TA-VFISvwZzR7sb2O2Q", "s": "1. Motivaci\u00f3n al cambio y logro de la abstinencia: En esta fase, se llevan a cabo t\u00e9cnicas terap\u00e9uticas cognitivas conductibles con sustento cient\u00edfico, ...", "id": "dP2MRdnC5YfF_M:"}, "filename": "32.jpg", "image_link": "http://www.carlosblanco.com/wp-content/uploads/2012/09/nueva-etapa-2.jpg", "original_filename": "nueva-etapa-2.jpg"}, "47": {"success": true, "google": {"ity": "jpg", "tw": 274, "ou": "http://www.esciclismo.com/actualidad/imagenes/g/vuelta_espana_etapa14_g_2012_unipublic.jpg", "rid": "qdwdP25fiqFRHM", "s": "15\u00aa etapa - 2 de septiembre: La Robla - Lagos de Covadonga - 186,7 Km. 16\u00aa etapa - 3 de septiembre: Gij\u00f3n - Cuitu Negru - 183,5 Km.", "sc": 1, "itg": false, "oh": 420, "th": 184, "pt": "Etapas de la Vuelta a Espa\u00f1a 2012", "ow": 624, "isu": "esciclismo.com", "ru": "http://www.esciclismo.com/especiales/vuelta_espana/2012/etapas.asp", "tu": "https://encrypted-tbn0.gstatic.com/images?q=tbn:ANd9GcSqWFRs7OEKqxuK3-YuLt_O9b6B77ktsow1ob8UIqJd9oTNrXZKaQ", "ct": 3, "id": "y62cNoFAjQ9a1M:"}, "filename": "47.jpg?cb=1268668281", "image_link": "http://image.slidesharecdn.com/primeraetapadeldesarrollopsico-sexual-100315155031-phpapp02/95/primera-etapa-del-desarrollo-psico-sexual-4-728.jpg?cb=1268668281", "original_filename": "primera-etapa-del-desarrollo-psico-sexual-4-728.jpg?cb=1268668281"}, "86": {"success": true, "google": {"isu": "colegioetapa.com.br", "cb": 18, "ou": "https://www.colegioetapa.com.br/home/assets//images/colegio_etapa_logo.png", "rid": "WC5GNl95rFfsNM", "s": "Curso ETAPA", "ity": "png", "pt": "Col\u00e9gio ETAPA | Matr\u00edculas", "itg": false, "cl": 9, "th": 80, "oh": 100, "sc": 1, "ow": 200, "cr": 9, "ru": "https://www.colegioetapa.com.br/matriculas_nova", "tu": "https://encrypted-tbn0.gstatic.com/images?q=tbn:ANd9GcTeln50Bu-CCJ_h3BNIUzYlMW-hkCz6gd3bmu9c1aiybSNgZ8At", "ct": 21, "tw": 160, "id": "zOH8jurAtXRu2M:"}, "filename": "86.jpg", "image_link": "https://i.ytimg.com/vi/pofAOsdXjxo/maxresdefault.jpg", "original_filename": "maxresdefault.jpg"}, "82": {"success": true, "google": {"isu": "twitter.com", "oh": 440, "tw": 225, "ou": "https://pbs.twimg.com/profile_images/697898219607556097/PNA2UtTl.jpg", "rid": "tZ94ZzTb6A0QLM", "ity": "jpg", "itg": false, "cl": 6, "th": 225, "pt": "ETAPA EP (@ETAPAOficial) | Twitter", "sc": 1, "ow": 440, "cr": 9, "ru": "https://twitter.com/etapaoficial", "tu": "https://encrypted-tbn2.gstatic.com/images?q=tbn:ANd9GcRuFNzz6EXbzkOBFvnPp2tfBr5tCHm1PO8gxF7dWwxOJBMWJXUvYw", "s": "", "id": "Qo2qRduXqdybgM:"}, "filename": "82.jpeg", "image_link": "http://www.eitb.eus/multimedia/images/2015/07/29/1742040/vuelta-perfil-11_original_imagen.jpeg", "original_filename": "vuelta-perfil-11_original_imagen.jpeg"}, "77": {"success": true, "google": {"ity": "png", "tw": 339, "ou": "http://www.etapa.net.ec/Portals/0/OpenContent/Files/2195/BANNER%20CDMA%20EN%20CAPAS-10.png", "rid": "1w3hVstbhYp5iM", "sc": 1, "itg": false, "oh": 431, "th": 149, "pt": "ETAPA EP - Servicios de Telefon\u00eda, Televisi\u00f3n, Internet, Agua ...", "ow": 980, "isu": "etapa.net.ec", "ru": "http://www.etapa.net.ec/", "tu": "https://encrypted-tbn1.gstatic.com/images?q=tbn:ANd9GcTWn0U9uXElCXog3sQ6Ym2PS4U1D7mtHqmKe_VmyHUUwioK4f7Q", "s": "ETAPA EP - Servicios de Telefon\u00eda, Televisi\u00f3n, Internet, Agua Potable, Alcantarillado de Cuenca - Ecuador &gt; Inicio", "id": "ClepNeqVOD5wyM:"}, "filename": "77.jpg", "image_link": "http://elembarazoprecoz.com/wp-content/uploads/2015/01/Etapas-del-embarazo-precoz.jpg", "original_filename": "Etapas-del-embarazo-precoz.jpg"}, "19": {"success": true, "google": {"cr": 3, "ct": 3, "cl": 3, "tw": 269, "th": 187}, "filename": "19.jpg", "image_link": "https://pbs.twimg.com/profile_images/226824413/Etapa_Twitter_400x400.jpg", "original_filename": "Etapa_Twitter_400x400.jpg"}, "96": {"success": true, "google": {"ity": "jpg", "tw": 259, "ou": "http://www.esciclismo.com/actualidad/imagenes/g/giro_italia_et08_g_2014_rcs.jpg", "rid": "wKr4UMjF0FchaM", "sc": 1, "itg": false, "oh": 619, "th": 195, "pt": "Etapas del Giro de Italia 2014", "ow": 822, "isu": "esciclismo.com", "ru": "http://www.esciclismo.com/especiales/giro_italia/2014/etapas.asp", "tu": "https://encrypted-tbn1.gstatic.com/images?q=tbn:ANd9GcSoZVpy_aKcdT8L3C8OFb7e5yAybSK0Oc8dcjsAvLhZYVO0lNkCBA", "s": "7\u00aa etapa - 16 de mayo: Frosinone - Foligno / 211 Km.", "id": "GkYJrghpD94VXM:"}, "filename": "96.jpg", "image_link": "https://www.euroresidentes.com/adolescentes/images/etapas_adolescents.jpg", "original_filename": "etapas_adolescents.jpg"}, "74": {"success": true, "google": {"ity": "jpg", "tw": 259, "ou": "http://image.slidesharecdn.com/lacrisisenlaetapadelaadolescencia-140408093944-phpapp02/95/la-crisis-en-la-etapa-de-la-adolescencia-1-638.jpg?cb=1396950172", "rid": "JLiBC3kDsmhv2M", "sc": 1, "itg": false, "oh": 479, "th": 194, "pt": "La crisis en la etapa de la adolescencia", "ow": 638, "isu": "es.slideshare.net", "ru": "http://es.slideshare.net/aalcalar/la-crisis-en-la-etapa-de-la-adolescencia", "tu": "https://encrypted-tbn3.gstatic.com/images?q=tbn:ANd9GcSMIbCMBAFbcM9xnqnULposQm2a8P00P74koKOmv0mcItJWGgRUsg", "s": "LA CRISIS EN LA ETAPA DE LA ADOLESCENCIA ...", "id": "L9Dz3X-g0VBz_M:"}, "filename": "74.jpg", "image_link": "http://www.esciclismo.com/actualidad/imagenes/g/giro_italia_et08_g_2014_rcs.jpg", "original_filename": "giro_italia_et08_g_2014_rcs.jpg"}, "52": {"success": true, "google": {"ity": "jpg", "cb": 3, "ou": "http://www.esciclismo.com/actualidad/imagenes/g/vuelta_espana_etapa15_g_2012_unipublic.jpg", "rid": "qdwdP25fiqFRHM", "s": "13\u00aa etapa - 31 de agosto: Santiago - Ferrol - 172,7 Km. 14\u00aa etapa - 1 de septiembre: Palas do Rei - Los Ancares - 149,2 Km. 15\u00aa etapa - 2 de septiembre: ...", "sc": 1, "itg": false, "oh": 400, "th": 180, "pt": "Etapas de la Vuelta a Espa\u00f1a 2012", "ow": 624, "isu": "esciclismo.com", "ru": "http://www.esciclismo.com/especiales/vuelta_espana/2012/etapas.asp", "tu": "https://encrypted-tbn2.gstatic.com/images?q=tbn:ANd9GcRJERSVWlcgGxofaap8joU3vWly-zjx8ZtdA2ckQ9lNSHs1IX-h", "ct": 12, "tw": 281, "id": "qYbCFB98tHrBlM:"}, "filename": "52.jpg?cb=1396950172", "image_link": "http://image.slidesharecdn.com/lacrisisenlaetapadelaadolescencia-140408093944-phpapp02/95/la-crisis-en-la-etapa-de-la-adolescencia-1-638.jpg?cb=1396950172", "original_filename": "la-crisis-en-la-etapa-de-la-adolescencia-1-638.jpg?cb=1396950172"}, "66": {"success": true, "google": {"ity": "jpg", "ou": "http://maternidadfacil.com/wp-content/uploads/2014/12/etapas-embarazo_2.jpg", "rid": "awzUfJgTBckjqM", "th": 120, "itg": false, "oh": 293, "tw": 420, "pt": "Las Etapas del embarazo mes a mes", "ow": 1024, "isu": "maternidadfacil.com", "ru": "http://maternidadfacil.com/las-etapas-del-embarazo-mes-a-mes/", "tu": "https://encrypted-tbn0.gstatic.com/images?q=tbn:ANd9GcQBtl1BvKJzWWRqh-sqxmScnHc8yJQ9BuD_3usF-ijGW9YUjIUzog", "s": "etapas-embarazo", "id": "9tbIhFqKvX_YpM:"}, "filename": "66.png", "image_link": "http://www.etapa.net.ec/Portals/0/OpenContent/Files/2195/BANNER CDMA EN CAPAS-12.png", "original_filename": "BANNER CDMA EN CAPAS-12.png"}, "40": {"success": true, "google": {"isu": "conmicelu.com", "cb": 21, "ou": "http://www.conmicelu.com/wp-content/uploads/2016/02/etapa-telecom.jpg", "rid": "lCze0zsVQVoxsM", "s": "", "ity": "jpg", "pt": "Gu\u00eda telef\u00f3nica de Cuenca - Etapa - Conmicelu", "itg": false, "cl": 6, "th": 183, "oh": 320, "sc": 1, "ow": 480, "cr": 6, "ru": "http://www.conmicelu.com/tramites/guia-telefonica-de-cuenca-etapa/", "tu": "https://encrypted-tbn0.gstatic.com/images?q=tbn:ANd9GcRb3qfTRORnDFY9KubwNpcx84qOnnQkqclwBwRIdDMwsfplFcTU0w", "ct": 21, "tw": 275, "id": "Wu8kBN07QpzgTM:"}, "filename": "40.jpg?cb=1372346828", "image_link": "http://image.slidesharecdn.com/etapaprenatalezpo-130627152553-phpapp02/95/etapa-prenatal-10-638.jpg?cb=1372346828", "original_filename": "etapa-prenatal-10-638.jpg?cb=1372346828"}, "12": {"success": true, "google": {"tw": 275, "th": 183}, "filename": "12.jpg", "image_link": "http://2.bp.blogspot.com/-gPpL3G6pVxs/UCoAQm0-J6I/AAAAAAAAEH8/o2Rf7s1TgG0/s1600/etapas-desarrollo.jpg", "original_filename": "etapas-desarrollo.jpg"}, "31": {"success": true, "google": {"isu": "listas.20minutos.es", "tw": 259, "ou": "http://st-listas.20minutos.es/images/2013-01/352965/list_640px.jpg?1358553766", "rid": "n48PndvwrUHnoM", "ity": "jpg", "itg": false, "oh": 480, "th": 194, "pt": "Ranking de 1er Campeonato de cine, Resultados de la etapa 5 ...", "ow": 640, "cr": 3, "ru": "http://listas.20minutos.es/lista/1er-campeonato-de-cine-resultados-de-la-etapa-5-352965/", "tu": "https://encrypted-tbn3.gstatic.com/images?q=tbn:ANd9GcRY6bWMsneQG7rDCY6yxw8uu3xJz3fFCymcgSmrJfXMsLQ7OiQXyw", "s": "1er Campeonato de cine, Resultados de la etapa 5\u00b0.", "id": "BMsTMkx1WMcCSM:"}, "filename": "31.jpg", "image_link": "https://image.freepik.com/vector-gratis/etapas-para-el-exito-infografia_23-2147508636.jpg", "original_filename": "etapas-para-el-exito-infografia_23-2147508636.jpg"}, "92": {"success": true, "google": {"isu": "embarazo10.com", "tw": 300, "ou": "http://static3.embarazo10.com/wp-content/uploads/gestacion-etapas-sintomas-del-embarazo.jpg", "rid": "N7L6iagG-a6dkM", "ity": "jpg", "itg": false, "oh": 362, "th": 168, "pt": "S\u00edntomas de embarazo: Gestaci\u00f3n y Etapas - Embarazo10.com", "ow": 644, "cr": 3, "ru": "http://embarazo10.com/gestacion-etapas-y-sintomas-del-embarazo/", "tu": "https://encrypted-tbn1.gstatic.com/images?q=tbn:ANd9GcTcPuBxz0HBI_WZectvI8_-TcQ2eFK_Cvnxe7cJLr4id7aR-xw8", "s": "gestacion-etapas-sintomas-del-embarazo.jpg", "id": "MSrl4rm3X8IzvM:"}, "filename": "92.png", "image_link": "http://www.etapainfantil.com/wp-content/uploads/2014/11/etapa-infantil-logohfb.png", "original_filename": "etapa-infantil-logohfb.png"}, "46": {"success": true, "google": {"isu": "colegioetapa.com.br", "cb": 3, "ou": "https://www.colegioetapa.com.br/home/assets//images/backgrounds/1920/bolsascolegio/2015_1/inscreva_se.jpg", "rid": "YSoWcEVadCNHIM", "s": "", "ity": "jpg", "pt": "Col\u00e9gio ETAPA | Desafio", "itg": false, "cl": 3, "th": 168, "oh": 1080, "sc": 1, "ow": 1920, "cr": 3, "ru": "https://www.colegioetapa.com.br/bolsascolegio/inscreva_se", "tu": "https://encrypted-tbn0.gstatic.com/images?q=tbn:ANd9GcRQaxGdc9ELmjNADThI7FNIb57MZurEnLGxAF5HM_go60fIrAJy", "ct": 9, "tw": 300, "id": "pN9Ia-8EvdW_ZM:"}, "filename": "46.jpg?cb=1390908689", "image_link": "http://image.slidesharecdn.com/etapaanal-140128112922-phpapp02/95/etapa-anal-sigmud-freud-1-638.jpg?cb=1390908689", "original_filename": "etapa-anal-sigmud-freud-1-638.jpg?cb=1390908689"}, "11": {"success": true, "google": {"tw": 259, "th": 194}, "filename": "11.png", "image_link": "http://cadenaradialvision.com/wp-content/uploads/2015/10/ETAPA-EP.png", "original_filename": "ETAPA-EP.png"}, "17": {"success": true, "google": {"tw": 349, "th": 144}, "filename": "17.png", "image_link": "https://www.sistemaetapa.com.br/home_site/assets//images/sistemaetapa-logofull.png", "original_filename": "sistemaetapa-logofull.png"}, "51": {"success": true, "google": {"ity": "jpg", "tw": 259, "ou": "http://image.slidesharecdn.com/etapa3v2-140227072205-phpapp02/95/etapa-3-v2-1-638.jpg?cb=1393485778", "rid": "BrjhGJNXtmPDlM", "sc": 1, "itg": false, "oh": 479, "th": 194, "pt": "Etapa 3 v2", "ow": 638, "isu": "es.slideshare.net", "ru": "http://es.slideshare.net/viveresponsable5/etapa-3-v2", "tu": "https://encrypted-tbn0.gstatic.com/images?q=tbn:ANd9GcSArVQ8xUOOmEya2oXajJLeH5o7lhg-yGGZdGqcE48qoCHjMeUlaQ", "s": "Etapa 3 ...", "id": "vx-Ea7_1OIO9AM:"}, "filename": "51.bmp", "image_link": "http://www.definicionabc.com/wp-content/uploads/etapa-litica.bmp", "original_filename": "etapa-litica.bmp"}, "42": {"success": true, "google": {"isu": "listas.20minutos.es", "cb": 3, "ou": "http://st-listas.20minutos.es/images/2013-03/358214/3966481_640px.jpg?1365798692", "rid": "mUdQ50SFH4yTqM", "s": "Ranking de ***DUELO DE NACIONES, EDICI\u00d3N 2*** ETAPA FINAL, VOTACIONES CERRADAS!! - Listas en 20minutos.es", "ity": "jpg", "pt": "Ranking de ***DUELO DE NACIONES, EDICI\u00d3N 2*** ETAPA FINAL ...", "itg": false, "cl": 15, "th": 225, "oh": 640, "sc": 1, "ow": 640, "cr": 3, "ru": "http://listas.20minutos.es/lista/duelo-de-naciones-edicion-2-etapa-final-votaciones-cerradas-358214/", "tu": "https://encrypted-tbn1.gstatic.com/images?q=tbn:ANd9GcRdZyLpP8VMYz6b3I3mCPia5MBoudZ4mJYvS0jw0_G1WUcbEZIk4g", "ct": 6, "tw": 225, "id": "tpLxh1JfgqiW4M:"}, "filename": "42.jpg", "image_link": "http://www.esciclismo.com/actualidad/imagenes/G/tour_de_francia_2013_et16_g.jpg", "original_filename": "tour_de_francia_2013_et16_g.jpg"}, "41": {"success": true, "google": {"isu": "twitter.com", "cb": 21, "ou": "https://pbs.twimg.com/profile_images/226824413/Etapa_Twitter_400x400.jpg", "rid": "eGTS2Le4ExIPFM", "s": "EAD ETAPA", "ity": "jpg", "pt": "EAD ETAPA (@ead_etapa) | Twitter", "itg": false, "cl": 3, "th": 225, "oh": 400, "sc": 1, "ow": 400, "cr": 3, "ru": "https://twitter.com/ead_etapa", "tu": "https://encrypted-tbn0.gstatic.com/images?q=tbn:ANd9GcSWceNdaJ5kR7cnbYUy31ltiSu1UU9lj1UsdU91pZbUZoNmuPcz", "ct": 21, "tw": 225, "id": "zW8sV-UaNdww_M:"}, "filename": "41.jpg?cb=1341839994", "image_link": "http://image.slidesharecdn.com/etapaprenatal22-120709131857-phpapp02/95/etapa-prenatal-2-2-1-728.jpg?cb=1341839994", "original_filename": "etapa-prenatal-2-2-1-728.jpg?cb=1341839994"}, "23": {"success": true, "google": {"isu": "etapa.net.ec", "cb": 21, "ou": "http://www.etapa.net.ec/portals/0/IconosGAD/ico_etapa_0.png", "rid": "1w3hVstbhYp5iM", "s": "Tweets por @ETAPAOficial", "ity": "png", "pt": "ETAPA EP - Servicios de Telefon\u00eda, Televisi\u00f3n, Internet, Agua ...", "itg": false, "cl": 6, "th": 68, "oh": 86, "sc": 1, "ow": 146, "cr": 6, "ru": "http://www.etapa.net.ec/", "tu": "https://encrypted-tbn3.gstatic.com/images?q=tbn:ANd9GcS8TFRzQd1LqfgKBMfmohcDiIeI6ASkEW_oN7BGusBxhXB4NMbWmQ", "ct": 21, "tw": 116, "id": "ws_3uFOoTZ4qQM:"}, "filename": "23.png", "image_link": "http://www.lamusicoterapia.com/wp-content/uploads/historia-de-la-musicoterapia01.png", "original_filename": "historia-de-la-musicoterapia01.png"}, "91": {"success": true, "google": {"ity": "jpg", "tw": 259, "ou": "http://image.slidesharecdn.com/desarrollohumano-110518222608-phpapp02/95/desarrollo-humano-11-728.jpg?cb=1305757754", "rid": "z0KWfoCwbhG2nM", "sc": 1, "itg": false, "oh": 546, "th": 194, "pt": "Desarrollo humano", "ow": 728, "isu": "es.slideshare.net", "ru": "http://es.slideshare.net/gisellemego/desarrollo-humano-8020383", "tu": "https://encrypted-tbn0.gstatic.com/images?q=tbn:ANd9GcR3NZOZpadpW6bf4UpLpFlL1x5J9GqBhabok2RAp4-WqWV6HobQ", "s": "ETAPA POST NATAL &lt;ul&gt;&lt;li&gt;Comprende desde el momento del nacimiento hasta la muerte y se divide en : &lt;/li&gt;&lt;/ul&gt;&lt;ul&gt;&lt;li&gt;La infancia de 0-6 a\u00f1os ...", "id": "EXNMuHXefFpVTM:"}, "filename": "91.y1pdS6t0_vNIC_6OLPxThsymVL7CiCfBOH__Goe7NAisXbGnVCsPAdKTPmqhaVlWIK-", "image_link": "http://byfiles.storage.live.com/y1pdS6t0_vNIC_6OLPxThsymVL7CiCfBOH__Goe7NAisXbGnVCsPAdKTPmqhaVlWIK-", "original_filename": "y1pdS6t0_vNIC_6OLPxThsymVL7CiCfBOH__Goe7NAisXbGnVCsPAdKTPmqhaVlWIK-"}, "87": {"success": true, "google": {"ity": "jpg", "tw": 299, "ou": "http://image.slidesharecdn.com/etapasdeldesarrollopsicosexual-140823092316-phpapp02/95/etapas-del-desarrollo-psicosexual-de-sigmund-freud-15-638.jpg?cb=1411413252", "rid": "w0vvQmsdmqvcvM", "sc": 1, "itg": false, "oh": 359, "th": 168, "pt": "Etapas del desarrollo Psicosexual de Sigmund Freud", "ow": 638, "isu": "es.slideshare.net", "ru": "http://es.slideshare.net/S12002059/etapas-del-desarrollo-psicosexual-de-sigmund-freud", "tu": "https://encrypted-tbn3.gstatic.com/images?q=tbn:ANd9GcRJJRpQ6oYq4sbj1vATqFYUj5CF4YTzDCCAkCEwnABUFlj2IhVZmw", "s": "Etapa Genital \uf075 Adem\u00e1s de los cambios psicol\u00f3gicos y f\u00edsicos el adolescente inicia una vida en grupo con sus iguales, lo que lleva a tener mucho contacto ...", "id": "SAsbF1vDDIoFVM:"}, "filename": "87.jpg", "image_link": "http://umvirtual.org/wp-content/uploads/etapa-profesional.jpg", "original_filename": "etapa-profesional.jpg"}, "95": {"success": true, "google": {"ity": "jpg", "tw": 259, "ou": "http://image.slidesharecdn.com/etapa-anal-2-1224293635233708-8/95/etapa-anal-2-2-728.jpg?cb=1224268536", "rid": "eOzI8AAkPcKM-M", "sc": 1, "itg": false, "oh": 546, "th": 194, "pt": "Etapa Anal 2", "ow": 728, "isu": "es.slideshare.net", "ru": "http://es.slideshare.net/alvistol/etapa-anal-2-presentation", "tu": "https://encrypted-tbn3.gstatic.com/images?q=tbn:ANd9GcQFweBunVBWoSpUucG8oVWYHFCbhiaTtXGL5U3Mi1ZypFP8S_N4", "s": "&lt;/li&gt;&lt;/ul&gt;&lt;ul&gt;&lt;li&gt;Caracter\u00edsticas &lt;/li&gt;&lt;/ul&gt;&lt;ul&gt;&lt;li&gt;Freud sit\u00faa esta segunda etapa del desarrollo de la personalidad entre los dos y tres a\u00f1os del ni\u00f1o; ...", "id": "3ZVfmUA6qMRr8M:"}, "filename": "95.png", "image_link": "http://www.etapa.com.br/home/assets//images/logo-etapa.png", "original_filename": "logo-etapa.png"}, "37": {"success": true, "google": {"ity": "png", "tw": 120, "ou": "https://www.etapa.com.br/grupoetapa/assets//images/curso-etapa-logo.png", "rid": "U6bfgzOERV77_M", "sc": 1, "itg": false, "oh": 53, "th": 47, "pt": "ETAPA | Grupo ETAPA Educacional", "ow": 133, "isu": "etapa.com.br", "ru": "https://www.etapa.com.br/en", "tu": "https://encrypted-tbn1.gstatic.com/images?q=tbn:ANd9GcRU_wsX6AxHzcZJdl3O-Zp5-JnpY-94xt8ltU5EZpzuGmiyogET", "s": "Curso ETAPA logo", "id": "mflR73pvaM_btM:"}, "filename": "37.jpg", "image_link": "https://lh6.googleusercontent.com/-BcjBfjHOC_8/TYPnqzxLjDI/AAAAAAAAAUg/UprH3OwsbT0/s1600/crecimiento.jpg", "original_filename": "crecimiento.jpg"}, "01": {"success": true, "google": {"ct": 18, "cl": 3, "cb": 18, "tw": 267, "th": 189}, "filename": "01.png", "image_link": "http://www.etapa.net.ec/portals/0/IconosGAD/ico_etapa_0.png", "original_filename": "ico_etapa_0.png"}, "59": {"success": true, "google": {"ity": "jpg", "tw": 297, "ou": "https://lh6.googleusercontent.com/-BcjBfjHOC_8/TYPnqzxLjDI/AAAAAAAAAUg/UprH3OwsbT0/s1600/crecimiento.jpg", "rid": "9ixBzipLsf4tVM", "sc": 1, "itg": false, "oh": 348, "th": 170, "pt": "Etapas del Desarrollo- Erick Erickson", "ow": 608, "isu": "elpsicoasesor.com", "ru": "http://elpsicoasesor.com/etapas-del-desarrollo-erick-erickson/", "tu": "https://encrypted-tbn1.gstatic.com/images?q=tbn:ANd9GcTEQfc-YeVqjiubbEEjozOwfloCBlHy3ly_AHCBw1u5H72WoEHiPQ", "s": "", "id": "d8BVdJdFbzPbwM:"}, "filename": "59.jpg?cb=1390908673", "image_link": "http://image.slidesharecdn.com/etapafalica-140128113034-phpapp02/95/etapa-falica-3-638.jpg?cb=1390908673", "original_filename": "etapa-falica-3-638.jpg?cb=1390908673"}, "89": {"success": true, "google": {"ity": "jpg", "tw": 281, "ou": "http://www.esciclismo.com/actualidad/imagenes/g/vuelta_espana_etapa16_g_2012_unipublic.jpg", "rid": "qdwdP25fiqFRHM", "s": "17\u00aa etapa - 5 de septiembre: Santander - Fuente D\u00e9 - 187,3 Km. 18\u00aa etapa - 6 de septiembre: Aguilar de Campoo - Valladolid - 204,5 Km.", "sc": 1, "itg": false, "oh": 400, "th": 180, "pt": "Etapas de la Vuelta a Espa\u00f1a 2012", "ow": 624, "isu": "esciclismo.com", "ru": "http://www.esciclismo.com/especiales/vuelta_espana/2012/etapas.asp", "tu": "https://encrypted-tbn1.gstatic.com/images?q=tbn:ANd9GcQA4HQ4NMlNBBRh39mwygOEJ5wR4av-KrZvSJuKOZbpM3rKN-kq", "ct": 9, "id": "7Mfh0CysKh8KpM:"}, "filename": "89.jpg", "image_link": "http://alejandriabolivar.com/wp-content/themes/alejandriabv/img/pic_familias_home.jpg", "original_filename": "pic_familias_home.jpg"}, "14": {"success": true, "google": {"tw": 287, "th": 176}, "filename": "14.png", "image_link": "https://www.etapa.com.br/grupoetapa/assets//images/colegio-etapa-logo.png", "original_filename": "colegio-etapa-logo.png"}, "93": {"success": true, "google": {"isu": "es.slideshare.net", "oh": 479, "tw": 259, "ou": "http://image.slidesharecdn.com/etapaoral-140127111347-phpapp02/95/etapa-oral-1-638.jpg?cb=1390821867", "rid": "jWeDnNSwHs3FhM", "ity": "jpg", "itg": false, "cl": 21, "th": 194, "pt": "etapa-oral-1-638.jpg?cb=1390821867", "ow": 638, "cr": 3, "ru": "http://es.slideshare.net/psicokaren/etapa-oral", "tu": "https://encrypted-tbn0.gstatic.com/images?q=tbn:ANd9GcSgWakXNiKjh1wrUjj24mt7vKZnM1MCpsLkt2owNBmb7W3DnbLj", "s": "Etapa oral ...", "id": "eBRArDzVbkVrKM:"}, "filename": "93.jpg", "image_link": "https://upload.wikimedia.org/wikipedia/commons/9/98/Etapa_2_Teide.jpg", "original_filename": "Etapa_2_Teide.jpg"}, "56": {"success": true, "google": {"isu": "telcoware.net", "cb": 9, "ou": "http://www.telcoware.net/wp-content/uploads/2013/03/etapa.jpg", "rid": "OGGVIXqIx-ERKM", "s": "Etapa Cuenca", "ity": "jpg", "pt": "Etapa Cuenca | TELCOWARE S.A.", "itg": false, "cl": 21, "th": 225, "oh": 663, "sc": 1, "ow": 663, "cr": 21, "ru": "http://www.telcoware.net/etapa-cuenca/", "tu": "https://encrypted-tbn0.gstatic.com/images?q=tbn:ANd9GcSYunjOjnGGdt_L26WP---_73JT0wbLW1yeZHNNArCknnSk1idsEw", "ct": 21, "tw": 225, "id": "VMMgeduzcwLdCM:"}, "filename": "56.jpg?cb=1354215785", "image_link": "http://image.slidesharecdn.com/etapapreescolar-121129190207-phpapp02/95/etapa-preescolar-1-638.jpg?cb=1354215785", "original_filename": "etapa-preescolar-1-638.jpg?cb=1354215785"}, "97": {"success": true, "google": {"ity": "jpg", "tw": 289, "ou": "http://www.esciclismo.com/actualidad/imagenes/g/tour_de_francia_2016_et08_g.jpg", "rid": "vrqXoY_BOhadzM", "sc": 1, "itg": false, "oh": 500, "th": 174, "pt": "Etapas del Tour de Francia 2016 - Recorrido", "ow": 830, "isu": "esciclismo.com", "ru": "http://www.esciclismo.com/especiales/tour_de_francia/etapas.asp", "tu": "https://encrypted-tbn2.gstatic.com/images?q=tbn:ANd9GcT66UginWSoTa9C_2F5Djp_qgv4IDFoCaFZe2tRpBadhF-aCk3i", "s": "8\u00aa etapa - 9 julio: Pau - Bagn\u00e8res-de-Luchon / 183 Km.", "id": "RXoe5qnw6VoaNM:"}, "filename": "97.jpg", "image_link": "http://images.slideplayer.es/3/1122832/slides/slide_3.jpg", "original_filename": "slide_3.jpg"}, "88": {"success": true, "google": {"isu": "etapa.net.ec", "cb": 18, "ou": "http://www.etapa.net.ec/Portals/0/OpenContent/Files/2195/BANNER%20CDMA%20EN%20CAPAS-12.png", "rid": "1w3hVstbhYp5iM", "s": "ETAPA EP - Servicios de Telefon\u00eda, Televisi\u00f3n, Internet, Agua Potable, Alcantarillado de Cuenca - Ecuador &gt; Inicio", "ity": "png", "pt": "ETAPA EP - Servicios de Telefon\u00eda, Televisi\u00f3n, Internet, Agua ...", "itg": false, "cl": 21, "th": 149, "oh": 431, "sc": 1, "ow": 980, "cr": 3, "ru": "http://www.etapa.net.ec/", "tu": "https://encrypted-tbn0.gstatic.com/images?q=tbn:ANd9GcSrlHYTUYFUMbUDh3-UnOq2vChGXQakntl63mA18VQtqpusOw2e-g", "ct": 21, "tw": 339, "id": "zDYkrVdlETSvyM:"}, "filename": "88.png", "image_link": "https://www.etapa.com.br/ambienteinspirador/assets//images/home/LogoRodape.png", "original_filename": "LogoRodape.png"}, "70": {"success": true, "google": {"ity": "jpg", "tw": 259, "ou": "http://image.slidesharecdn.com/etapafalica-140128113034-phpapp02/95/etapa-falica-2-638.jpg?cb=1390908673", "rid": "G_7Mo_S-Wdt7OM", "sc": 1, "itg": false, "oh": 479, "th": 194, "pt": "Etapa falica", "ow": 638, "isu": "es.slideshare.net", "ru": "http://es.slideshare.net/PsicoEdith5/etapa-falica", "tu": "https://encrypted-tbn1.gstatic.com/images?q=tbn:ANd9GcSvkxAQdk-XimuAGqkQIy3xIs25O1DtZRZp0oEKtoXzSLLYVAsxbQ", "s": "ETAPA F\u00c1LICA: \u2022 3-6 a\u00f1os de edad. \u2022 Los \u00f3rganos genitales se vuelven una fuente destacada de placer durante este per\u00edodo.", "id": "EtLZa12rVqnBuM:"}, "filename": "70.jpg", "image_link": "http://static3.embarazo10.com/wp-content/uploads/gestacion-etapas-sintomas-del-embarazo.jpg", "original_filename": "gestacion-etapas-sintomas-del-embarazo.jpg"}, "81": {"success": true, "google": {"isu": "es.slideshare.net", "oh": 479, "cb": 3, "ou": "http://image.slidesharecdn.com/etapafalica-140128113034-phpapp02/95/etapa-falica-3-638.jpg?cb=1390908673", "rid": "G_7Mo_S-Wdt7OM", "tw": 259, "ity": "jpg", "itg": false, "cl": 6, "th": 194, "pt": "Etapa falica", "ow": 638, "cr": 6, "ru": "http://es.slideshare.net/PsicoEdith5/etapa-falica", "tu": "https://encrypted-tbn0.gstatic.com/images?q=tbn:ANd9GcS0V-zjtmIrcpazU2jFbTXP_r_qtopFpj1pVVzC1wLTuJmvD8L_", "s": "La curiosidad respecto al cuerpo puede comenzar mucho antes \u2022 encuentra con asombro sus manos y sus pies \u2022 incluso puede descubrir los \u00f3rganos genitales ...", "id": "Hv5ARiZ8lpHvVM:"}, "filename": "81.GIF", "image_link": "http://www.editoriallapaz.org/Etapa 1-3.GIF", "original_filename": "Etapa 1-3.GIF"}, "22": {"success": true, "google": {"cr": 21, "tw": 376, "th": 134, "ct": 21, "cl": 18, "cb": 3}, "filename": "22.jpg?cb=1300108723", "image_link": "http://image.slidesharecdn.com/etapasesoriomotriz-110314131806-phpapp02/95/etapa-sesoriomotriz-1-728.jpg?cb=1300108723", "original_filename": "etapa-sesoriomotriz-1-728.jpg?cb=1300108723"}, "45": {"success": true, "google": {"isu": "lamusicoterapia.com", "oh": 400, "tw": 312, "ou": "http://www.lamusicoterapia.com/wp-content/uploads/historia-de-la-musicoterapia01.png", "rid": "TIXDGpMj-ZPkLM", "ity": "png", "itg": false, "cl": 6, "th": 162, "pt": "Etapa cient\u00edfica - Musicoterapia", "ow": 770, "cr": 12, "ru": "http://www.lamusicoterapia.com/historia-de-la-musicoterapia-3/", "tu": "https://encrypted-tbn2.gstatic.com/images?q=tbn:ANd9GcTKklrd77JPfxQvDTj_rUxEKumwm8bpww-G3MUqJfWJIH_urCuycA", "s": "Etapa cient\u00edfica (tercera etapa)", "id": "vXKiivTrk515jM:"}, "filename": "45.png", "image_link": "http://www.etapasdesarrollohumano.com/img/etapas/etapadesarrollo-prenatal.png", "original_filename": "etapadesarrollo-prenatal.png"}, "54": {"success": true, "google": {"isu": "carlosblanco.com", "oh": 225, "tw": 300, "ou": "http://www.carlosblanco.com/wp-content/uploads/2012/09/nueva-etapa-2.jpg", "rid": "oxw5Sw5jKRC8JM", "ity": "jpg", "itg": false, "cl": 6, "th": 168, "pt": "Empieza una nueva etapa personal y profesional | Carlos Blanco", "ow": 401, "cr": 9, "ru": "http://carlosblanco.com/2012/09/14/empieza-una-nueva-etapa-personal-y-profesional/", "tu": "https://encrypted-tbn2.gstatic.com/images?q=tbn:ANd9GcQMsJgrmzzIfLNaA1KV3GMimVb7UGPLStqLTTOt_LeT2VamRElioQ", "s": "Para acabar. adem\u00e1s de los cambios familiares y profesionales, a nivel personal tambi\u00e9n afronto una nueva y motivante etapa en la que espero ser muy feliz y ...", "id": "DW--AGdy4a40sM:"}, "filename": "54.jpg", "image_link": "http://2.bp.blogspot.com/-S3Yr7irVXOQ/T10c1GDwR3I/AAAAAAAABaM/lwYpaVwZj6o/s1600/cambio.jpg", "original_filename": "cambio.jpg"}, "50": {"success": true, "google": {"isu": "holamundo.mx", "cb": 6, "ou": "http://www.holamundo.mx/wp-content/uploads/2013/12/etapas.jpg", "rid": "Q8qvzARrQBepeM", "s": "Startup: salto de fe al profundo acantilado de los negocios. | holaMundo", "ity": "jpg", "pt": "Startup: salto de fe al profundo acantilado de los negocios ...", "itg": false, "cl": 3, "th": 189, "oh": 1754, "sc": 1, "ow": 2480, "cr": 3, "ru": "http://www.holamundo.mx/startup-salto-de-fe-al-profundo-acantilado-de-los-negocios/", "tu": "https://encrypted-tbn1.gstatic.com/images?q=tbn:ANd9GcQqDzuktKyKDWDwdKNVLx2HMplnIPzVuN_2-J8TRU6B-j2SY0SL", "ct": 3, "tw": 267, "id": "teFVfyBeTsaPBM:"}, "filename": "50.jpg?cb=1370210789", "image_link": "http://image.slidesharecdn.com/etapaspsicosexualesdesarrollohumano-130602220532-phpapp01/95/etapas-psicosexuales-del-desarrollo-humano-6-638.jpg?cb=1370210789", "original_filename": "etapas-psicosexuales-del-desarrollo-humano-6-638.jpg?cb=1370210789"}, "21": {"success": true, "google": {"tw": 279, "th": 181}, "filename": "21.jpg", "image_link": "https://pbs.twimg.com/profile_images/651830579495837697/HNHZbb8m.jpg", "original_filename": "HNHZbb8m.jpg"}, "49": {"success": true, "google": {"isu": "tikeandoenzallla.blogspot.com", "oh": 257, "tw": 240, "ou": "http://www.urbecom.com/blog/wp-content/uploads/2009/07/etapas-del-plan-de-marketing-300x257.jpg", "rid": "NWdYGIGPxcwoPM", "s": "Las distintas etapas por las que podr\u00eda pasar el proyecto ser\u00edan:", "ity": "jpg", "itg": false, "cl": 21, "th": 205, "pt": "TIK-eando en Zalla: octubre 2010", "sc": 1, "ow": 300, "cr": 9, "ru": "http://tikeandoenzallla.blogspot.com/2010_10_01_archive.html", "tu": "https://encrypted-tbn2.gstatic.com/images?q=tbn:ANd9GcQEk785wWcQNo_SYDoizt689ENopbfJ0DDnWlfJDtQtOdZXhkxi", "ct": 3, "id": "sZki32iH7ZQXVM:"}, "filename": "49.png", "image_link": "http://www.etapa.net.ec/Portals/0/OpenContent/Files/2195/BANNER CDMA EN CAPAS-11.png", "original_filename": "BANNER CDMA EN CAPAS-11.png"}, "48": {"success": true, "google": {"ity": "jpg", "tw": 259, "ou": "http://image.slidesharecdn.com/6a11aos-100622151613-phpapp02/95/etapa-escolar-1-728.jpg?cb=1277220615", "rid": "8qPP1QUFXZtk6M", "sc": 1, "itg": false, "oh": 546, "th": 194, "pt": "Etapa Escolar", "ow": 728, "isu": "es.slideshare.net", "ru": "http://es.slideshare.net/kristhell86/etapa-escolar-4578388", "tu": "https://encrypted-tbn0.gstatic.com/images?q=tbn:ANd9GcS0HkJUPkS3R_gkPonFzyWbUKn0Gsoyn0EWadsaiGDgcSRmYSkeGg", "s": "ETAPA ESCOLAR ( 6 a 11 a\u00f1os ) Bases para una Vida Saludable ...", "id": "tXJ4EH9p5i9VJM:"}, "filename": "48.jpg?cb=1390908673", "image_link": "http://image.slidesharecdn.com/etapafalica-140128113034-phpapp02/95/etapa-falica-2-638.jpg?cb=1390908673", "original_filename": "etapa-falica-2-638.jpg?cb=1390908673"}, "57": {"success": true, "google": {"isu": "newclick.es", "oh": 218, "tw": 174, "ou": "http://www.newclick.es/imagenes/etapas-del-diseno-de-una-pagina-web.jpg", "rid": "RVTuZHratMdkLM", "ity": "jpg", "itg": false, "cl": 21, "th": 174, "pt": "Etapas creaci\u00f3n del Dise\u00f1o Web - Fases de una p\u00e1gina web", "sc": 1, "ow": 218, "cr": 21, "ru": "http://www.newclick.es/etapas-diseno-web-creacion-diseno-web.php", "tu": "https://encrypted-tbn1.gstatic.com/images?q=tbn:ANd9GcQ0hPHqxZTtFaOHsN6DXk5RlVOQFOQMZKjtS21SSH0Q-I2reizEZg", "s": "Etapas del dise\u00f1o web", "id": "asXp0WPyr09OqM:"}, "filename": "57.png", "image_link": "http://www.blogtrw.com/wp-content/uploads/matriz-madurez-de-negocio-y-etapa-de-desarrollo-de-producto.png", "original_filename": "matriz-madurez-de-negocio-y-etapa-de-desarrollo-de-producto.png"}, "44": {"success": true, "google": {"isu": "es.slideshare.net", "cb": 3, "ou": "http://image.slidesharecdn.com/etapasesoriomotriz-110314131806-phpapp02/95/etapa-sesoriomotriz-1-728.jpg?cb=1300108723", "rid": "ear1asVggQvJqM", "s": "Etapa Sesoriomotriz.&lt;br /&gt;Luz Mery De Alo Molinares.", "ity": "jpg", "pt": "Etapa sesoriomotriz", "itg": false, "cl": 15, "th": 194, "oh": 546, "sc": 1, "ow": 728, "cr": 6, "ru": "http://es.slideshare.net/luzmerydealo/etapa-sesoriomotriz", "tu": "https://encrypted-tbn0.gstatic.com/images?q=tbn:ANd9GcSuNsaHiV0HeKIe73fsh8k7o7mWQnbK9xH85GjJRFcyXbPXKB28", "ct": 12, "tw": 259, "id": "Y0NMP87tIrDCIM:"}, "filename": "44.jpg", "image_link": "http://maternidadfacil.com/wp-content/uploads/2014/12/etapas-embarazo_2.jpg", "original_filename": "etapas-embarazo_2.jpg"}, "20": {"success": true, "google": {"ct": 18, "cl": 3, "cb": 18, "tw": 267, "th": 189}, "filename": "20.jpg?1365798692", "image_link": "http://st-listas.20minutos.es/images/2013-03/358214/3966481_640px.jpg?1365798692", "original_filename": "3966481_640px.jpg?1365798692"}, "13": {"success": true, "google": {"tw": 258, "th": 196}, "filename": "13.png", "image_link": "http://www.etapa.net.ec/Portals/0/logoMainNew.png", "original_filename": "logoMainNew.png"}, "25": {"success": true, "google": {"isu": "etapa.com.br", "cb": 3, "ou": "https://www.etapa.com.br/ambienteinspirador/assets//images/home/logotipo.png", "rid": "QCjm2id_zWhN5M", "s": "ETAPA Resultados", "ity": "png", "itg": false, "oh": 238, "th": 190, "pt": "ETAPA | Escolha acertada", "sc": 1, "ow": 243, "cr": 9, "ru": "https://www.etapa.com.br/ambienteinspirador/", "tu": "https://encrypted-tbn2.gstatic.com/images?q=tbn:ANd9GcSKZMyfWMQV3zqtq61ZSMqZ9XH6MPNijWo7vZuDRaVVplyVmxSrCw", "ct": 6, "tw": 194, "id": "pXmOXI_OwVxktM:"}, "filename": "25.jpg", "image_link": "http://www.esciclismo.com/actualidad/imagenes/g/vuelta_espana_etapa14_g_2012_unipublic.jpg", "original_filename": "vuelta_espana_etapa14_g_2012_unipublic.jpg"}, "02": {"success": true, "google": {"ct": 12, "cl": 3, "cb": 9, "tw": 271, "th": 186}, "filename": "02.png", "image_link": "http://correvedile.com/images/danielgarcia/etapas-vida.png", "original_filename": "etapas-vida.png"}, "39": {"success": true, "google": {"ity": "png", "tw": 379, "ou": "https://www.sistemaetapa.com.br/home_site/assets//images/sistemaetapa-logofull.png", "rid": "SJ_tSr47qT2z0M", "sc": 1, "itg": false, "oh": 90, "th": 72, "pt": "Sistema ETAPA | Home", "ow": 474, "isu": "sistemaetapa.com.br", "ru": "https://www.sistemaetapa.com.br/", "tu": "https://encrypted-tbn0.gstatic.com/images?q=tbn:ANd9GcTtYEo4ht8vw1PMnLkTxm0SGVNZCfMSzmH5KsuQuULmHgUSkaRz", "s": "Home; Quem Somos", "id": "hHAYeRbJec7yDM:"}, "filename": "39.jpg", "image_link": "http://www.monografias.com/trabajos102/desarrollo-psicosexual-infancia/image006.jpg", "original_filename": "image006.jpg"}, "98": {"success": true, "google": {"isu": "cvc.cervantes.es", "tw": 313, "ou": "http://cvc.cervantes.es/img/camino_santiago/etapa1_portada.jpg", "rid": "fHNyl7SUhw08fM", "ity": "jpg", "itg": false, "oh": 240, "th": 161, "pt": "CVC. El Camino de Santiago. El Camino. Primera etapa.", "ow": 466, "cr": 3, "ru": "http://cvc.cervantes.es/artes/camino_santiago/primera_etapa/", "tu": "https://encrypted-tbn0.gstatic.com/images?q=tbn:ANd9GcQR7bWWF0A34vdCmFZ2BpS96k7Tv8yShv6olCTlCZtNbZkPzLZd", "s": "Conjunto pict\u00f3rico de Bag\u00fces. Resurrecci\u00f3n de L\u00e1zaro", "id": "oxbsELXsG8DgKM:"}, "filename": "98.jpg", "image_link": "https://gijonenbici.files.wordpress.com/2013/05/tappa_dettagli_tecnici_altimetria_10.jpg", "original_filename": "tappa_dettagli_tecnici_altimetria_10.jpg"}, "34": {"success": true, "google": {"isu": "euroresidentes.com", "cb": 3, "ou": "http://2.bp.blogspot.com/-gPpL3G6pVxs/UCoAQm0-J6I/AAAAAAAAEH8/o2Rf7s1TgG0/s1600/etapas-desarrollo.jpg", "rid": "AEegoR8FLuKQAM", "s": "Las etapas del desarrollo humano se dividen en 6:", "ity": "jpg", "pt": "Cada etapa del desarrollo humano - Sentir bien", "itg": false, "cl": 9, "th": 183, "oh": 282, "sc": 1, "ow": 425, "cr": 12, "ru": "https://www.euroresidentes.com/estilo-de-vida/sentir-bien/cada-etapa-del-desarrollo-humano", "tu": "https://encrypted-tbn3.gstatic.com/images?q=tbn:ANd9GcRV4rA3gsVF7WbkUr9l9SBVCtnOWA1CKi0onqS65bh3U7PfKy0b", "ct": 9, "tw": 276, "id": "-Hrfm61QKoahNM:"}, "filename": "34.jpg", "image_link": "http://www.telcoware.net/wp-content/uploads/2013/03/etapa.jpg", "original_filename": "etapa.jpg"}, "29": {"success": true, "google": {"ity": "", "tw": 354, "ou": "http://www.cuenca.gob.ec/?q=system/files/etapaLogo.gif", "rid": "GDU3JKzvVZPXbM", "sc": 1, "itg": false, "oh": 230, "th": 142, "pt": "Empresa Municipal de Telecomunicaciones, Agua Potable y ...", "ow": 570, "isu": "cuenca.gov.ec", "ru": "http://www.cuenca.gov.ec/?q=node/275", "tu": "https://encrypted-tbn0.gstatic.com/images?q=tbn:ANd9GcTZnWyfmBH4MAfVFY3gCe-ZNRUlKDxiWxSa_UvwfsJ9JB9n8eYu", "s": "Empresa Municipal de Telecomunicaciones, Agua Potable y Saneamiento", "id": "b7NsQeKFzSQtUM:"}, "filename": "29.jpg?cb=1393485778", "image_link": "http://image.slidesharecdn.com/etapa3v2-140227072205-phpapp02/95/etapa-3-v2-1-638.jpg?cb=1393485778", "original_filename": "etapa-3-v2-1-638.jpg?cb=1393485778"}, "04": {"success": true, "google": {"tw": 256, "th": 197}, "filename": "04.jpg", "image_link": "http://www.emprenden.net/wp-content/uploads/2009/09/steps1-300x300.jpg", "original_filename": "steps1-300x300.jpg"}, "63": {"success": true, "google": {"isu": "es.slideshare.net", "cb": 21, "ou": "http://image.slidesharecdn.com/etapaprenatal22-120709131857-phpapp02/95/etapa-prenatal-2-2-1-728.jpg?cb=1341839994", "rid": "ua_-zQPMxyKCjM", "s": "Etapa PrenatalMiranda AltunaFiorella FierroKiara MirandaPriscilla Scamarone ...", "ity": "jpg", "itg": false, "oh": 546, "th": 194, "pt": "Etapa prenatal (2) (2)", "ow": 728, "cr": 3, "ru": "http://es.slideshare.net/consorcionsp/etapa-prenatal-2-2", "tu": "https://encrypted-tbn3.gstatic.com/images?q=tbn:ANd9GcRcjfdfjzuAOOD-T38WqGyHqTCW9ky-RzsZnhJ_IGda2j_Ii9Zc", "ct": 9, "tw": 259, "id": "B6SXc_WccIoUwM:"}, "filename": "63.jpg", "image_link": "http://www.esciclismo.com/actualidad/imagenes/g/vuelta_espana_etapa20_g_2013_unipublic.jpg", "original_filename": "vuelta_espana_etapa20_g_2013_unipublic.jpg"}, "94": {"success": true, "google": {"ity": "jpg", "tw": 251, "ou": "https://estudiandotusistemadigestivo.files.wordpress.com/2012/06/10919222.jpg", "rid": "5VY8BGAzDUe1JM", "sc": 1, "itg": false, "oh": 320, "th": 201, "pt": "Etapas de la enfermedad | Sistema Digestivo", "ow": 400, "isu": "estudiandotusistemadigestivo.wordpress.com", "ru": "https://estudiandotusistemadigestivo.wordpress.com/etapas-de-la-enfermedad/", "tu": "https://encrypted-tbn1.gstatic.com/images?q=tbn:ANd9GcR5sKZa5u0wFgXTZhNHU1gETd256pfN6BnN-fztLMwOQ8Eb1G_JIg", "s": "Etapa IV: El c\u00e1ncer ha llegado a otros \u00f3rganos del cuerpo (principalmente tiende a invadir el h\u00edgado y los pulmones).", "id": "bnXNUN_6SLI1bM:"}, "filename": "94.png", "image_link": "http://www.etapasdesarrollohumano.com/img/etapas/etapadesarrollo-ancianidad.png", "original_filename": "etapadesarrollo-ancianidad.png"}, "09": {"success": true, "google": {"cr": 3, "tw": 281, "cl": 3, "cb": 3, "th": 179}, "filename": "09.jpg?1358553766", "image_link": "http://st-listas.20minutos.es/images/2013-01/352965/list_640px.jpg?1358553766", "original_filename": "list_640px.jpg?1358553766"}, "10": {"success": true, "google": {"cr": 6, "tw": 266, "cb": 3, "th": 189}, "filename": "10.jpg", "image_link": "https://camilomendoza.files.wordpress.com/2011/11/etapas3.jpg", "original_filename": "etapas3.jpg"}, "79": {"success": true, "google": {"isu": "blogtrw.com", "cb": 6, "ou": "http://www.blogtrw.com/wp-content/uploads/matriz-madurez-de-negocio-y-etapa-de-desarrollo-de-producto.png", "rid": "UE3mnMEna9MdJM", "s": "matriz madurez de negocio y etapa de desarrollo de producto", "ity": "png", "pt": "Las 6 etapas de financiaci\u00f3n de modelos de negocio y emprendedores ...", "itg": false, "cl": 3, "th": 168, "oh": 337, "sc": 1, "ow": 601, "cr": 3, "ru": "http://www.blogtrw.com/2011/04/las-6-etapas-de-financiacion-de-modelos-de-negocio-y-emprendedores/", "tu": "https://encrypted-tbn0.gstatic.com/images?q=tbn:ANd9GcQbbxvQUkwaE8bfncbwfySjWJxWuUov_bZ8VzC5n6LExLdd-LHZ4A", "ct": 6, "tw": 300, "id": "1eeAl2jzt7eLNM:"}, "filename": "79.jpg", "image_link": "http://www.colegioetapa.com.br/home/assets//images/sobre_o_etapa/grande/colegio-etapa-sp-informatica.jpg", "original_filename": "colegio-etapa-sp-informatica.jpg"}, "07": {"success": true, "google": {"cr": 3, "tw": 280, "th": 60, "ct": 6, "cl": 3, "cb": 15}, "filename": "07.gif", "image_link": "http://www.cuenca.gob.ec/?q=system/files/etapaLogo.gif", "original_filename": "etapaLogo.gif"}, "69": {"success": true, "google": {"ity": "jpg", "tw": 259, "ou": "http://image.slidesharecdn.com/primeraetapadeldesarrollopsico-sexual-100315155031-phpapp02/95/primera-etapa-del-desarrollo-psico-sexual-4-728.jpg?cb=1268668281", "rid": "u8mromd7Wd0vzM", "sc": 1, "itg": false, "oh": 546, "th": 194, "pt": "Primera Etapa Del Desarrollo Psico Sexual", "ow": 728, "isu": "es.slideshare.net", "ru": "http://es.slideshare.net/xpiilii/primera-etapa-del-desarrollo-psico-sexual", "tu": "https://encrypted-tbn2.gstatic.com/images?q=tbn:ANd9GcQS5ML3j1mgEzo32vD2ugGbvXL2m4QJy2vCxIhfedGhcTvqizQS", "s": "Etapa oral (hasta 18 meses) &lt;ul&gt;&lt;li&gt;Es el primer momento en la evoluci\u00f3n de la personalidad del individuo. &lt;/li&gt;&lt;/ul&gt;&lt;ul&gt;&lt;li&gt;Inicia en el nacimiento, ...", "id": "mbtK37is_ROX2M:"}, "filename": "69.jpg?cb=1305757754", "image_link": "http://image.slidesharecdn.com/desarrollohumano-110518222608-phpapp02/95/desarrollo-humano-11-728.jpg?cb=1305757754", "original_filename": "desarrollo-humano-11-728.jpg?cb=1305757754"}, "18": {"success": true, "google": {"tw": 145, "th": 151}, "filename": "18.jpg", "image_link": "http://www.conmicelu.com/wp-content/uploads/2016/02/etapa-telecom.jpg", "original_filename": "etapa-telecom.jpg"}, "85": {"success": true, "google": {"ity": "jpg", "tw": 270, "ou": "http://www.esciclismo.com/actualidad/imagenes/g/vuelta_espana_etapa20_g_2013_unipublic.jpg", "rid": "D0BsF85KJuCK_M", "s": "19\u00aa etapa - 13 de septiembre: S. Vicente de la Barquera - Alto Naranco / 181,0 Km.", "sc": 1, "itg": false, "oh": 450, "th": 187, "pt": "Etapas de la Vuelta a Espa\u00f1a 2013", "ow": 650, "isu": "esciclismo.com", "ru": "http://www.esciclismo.com/especiales/vuelta_espana/2013/etapas.asp", "tu": "https://encrypted-tbn2.gstatic.com/images?q=tbn:ANd9GcQ0cN8S7rkd6B5XvVg-EkhrRlbNrqKMUIUCEnKDozmR94-X2DLn", "ct": 9, "id": "QVGWOPpoXFNwUM:"}, "filename": "85.jpg", "image_link": "http://suite101.intl.s3.amazonaws.com/article_images/95066_net_ptg0068407.jpg", "original_filename": "95066_net_ptg0068407.jpg"}, "53": {"success": true, "google": {"ity": "jpg", "tw": 225, "ou": "https://image.freepik.com/vector-gratis/etapas-para-el-exito-infografia_23-2147508636.jpg", "rid": "7jesjTaCIfxUxM", "sc": 1, "itg": false, "oh": 626, "th": 225, "pt": "Etapa | Fotos y Vectores gratis", "ow": 626, "isu": "freepik.es", "ru": "http://www.freepik.es/fotos-vectores-gratis/etapa", "tu": "https://encrypted-tbn3.gstatic.com/images?q=tbn:ANd9GcRAwQdpHacFlf_IbMK-60MKvgeurIVNhCRFmSy8AWK4qxMsZ1s-Cw", "s": "Etapas para el \u00e9xito infograf\u00eda", "id": "LACnDy8biZYsgM:"}, "filename": "53.jpg", "image_link": "https://i.ytimg.com/vi/ck6cIJ0DvSk/maxresdefault.jpg", "original_filename": "maxresdefault.jpg"}, "62": {"success": true, "google": {"ity": "jpg", "tw": 259, "ou": "http://image.slidesharecdn.com/etapaprenatalezpo-130627152553-phpapp02/95/etapa-prenatal-10-638.jpg?cb=1372346828", "rid": "zMy55UBxgZq1wM", "sc": 1, "itg": false, "oh": 479, "th": 194, "pt": "Etapa prenatal", "ow": 638, "isu": "es.slideshare.net", "ru": "http://es.slideshare.net/richarduarteacosta/etapa-prenatal-23589410", "tu": "https://encrypted-tbn1.gstatic.com/images?q=tbn:ANd9GcQZB3yFdwSEZ-LOornclErQXfeNbNl8SHUQf2Giu2SsOUGgmjKp", "s": "ETAPA PRENATAL Su desarrollo es: \uf0d8Desarrollo F\u00edsico -Etapa Germinal -Etapa Embrionaria -Etapa Fetal \uf0d8Desarrollo Cognoscitivo \uf0d8Desarrollo Psicosocial ...", "id": "8nMVAFst-FBFDM:"}, "filename": "62.jpg", "image_link": "http://media.djmania.net/images/extra/Etapa_de_potencia_BHM_-_200_W_RMS__-_AMP-700.jpg", "original_filename": "Etapa_de_potencia_BHM_-_200_W_RMS__-_AMP-700.jpg"}, "67": {"success": true, "google": {"isu": "etapasdesarrollohumano.com", "cb": 3, "ou": "http://www.etapasdesarrollohumano.com/img/etapas/etapadesarrollo-prenatal.png", "rid": "ATtc6L4NPwHd3M", "s": "La Etapa Prenatal o Fase Pre-natal, primera de las etapas en el desarrollo del ser humano", "ity": "png", "pt": "Etapa Prenatal - Etapas del desarrollo humano", "itg": false, "cl": 9, "th": 160, "oh": 200, "sc": 1, "ow": 200, "cr": 9, "ru": "http://www.etapasdesarrollohumano.com/etapas/prenatal", "tu": "https://encrypted-tbn2.gstatic.com/images?q=tbn:ANd9GcS2HVDQIebU-Obxk41OrtWEQ-Df6V0Cpc_0oOnnFicyoGXqXJyDyg", "ct": 6, "tw": 160, "id": "PB7aIgZY-SsYTM:"}, "filename": "67.jpg", "image_link": "http://www.esciclismo.com/actualidad/imagenes/g/vuelta_espana_etapa16_g_2012_unipublic.jpg", "original_filename": "vuelta_espana_etapa16_g_2012_unipublic.jpg"}, "75": {"success": true, "google": {"isu": "youtube.com", "oh": 746, "cb": 21, "ou": "https://i.ytimg.com/vi/ck6cIJ0DvSk/maxresdefault.jpg", "rid": "Mgzuf5ZtOzhwJM", "tw": 300, "ity": "jpg", "itg": false, "cl": 18, "th": 168, "pt": "Etapa de definici\u00f3n - como la hice - explicaci\u00f3n f\u00e1cil - YouTube", "sc": 1, "ow": 1328, "cr": 18, "ru": "https://www.youtube.com/watch?v=ck6cIJ0DvSk", "tu": "https://encrypted-tbn1.gstatic.com/images?q=tbn:ANd9GcSohqrDuJc7Vi4SXIcX7R9Zq7y-FEhtS4EIQa7Pe6WYrN9Rygrw", "s": "Etapa de definici\u00f3n - como la hice - explicaci\u00f3n f\u00e1cil", "id": "GlwBcVpmwueCrM:"}, "filename": "75.jpg", "image_link": "http://www.esciclismo.com/actualidad/imagenes/g/tour_de_francia_2016_et08_g.jpg", "original_filename": "tour_de_francia_2016_et08_g.jpg"}, "68": {"success": true, "google": {"ity": "jpg", "tw": 259, "ou": "http://image.slidesharecdn.com/etapaanal-140128112922-phpapp02/95/etapa-anal-sigmud-freud-1-638.jpg?cb=1390908689", "rid": "Rq7HRcWtQ_0GuM", "sc": 1, "itg": false, "oh": 479, "th": 194, "pt": "Etapa anal sigmud freud", "ow": 638, "isu": "es.slideshare.net", "ru": "http://es.slideshare.net/Jesicuenta2014/etapa-anal", "tu": "https://encrypted-tbn2.gstatic.com/images?q=tbn:ANd9GcRXUXJt0apKmmpbxvz00nHVE3WBBuMy3Z7LxIaAof2k7oxwwAQs", "s": "fase anal Etapa psicosexual ...", "id": "81SWOpMKYpSV8M:"}, "filename": "68.jpg?cb=1386343768", "image_link": "http://image.slidesharecdn.com/etapasdellenguaje-131206152836-phpapp02/95/etapas-del-lenguaje-0-5-aos-7-638.jpg?cb=1386343768", "original_filename": "etapas-del-lenguaje-0-5-aos-7-638.jpg?cb=1386343768"}, "05": {"success": true, "google": {"tw": 402, "th": 98}, "filename": "05.jpg", "image_link": "http://www.malldelrio.com/wp-content/uploads/2015/04/l-etapa.jpg", "original_filename": "l-etapa.jpg"}, "78": {"success": true, "google": {"ity": "jpg", "tw": 259, "ou": "http://image.slidesharecdn.com/etapapreescolar-121129190207-phpapp02/95/etapa-preescolar-1-638.jpg?cb=1354215785", "rid": "Q7K9br9a0VuR3M", "sc": 1, "itg": false, "oh": 479, "th": 194, "pt": "Etapa preescolar", "ow": 638, "isu": "es.slideshare.net", "ru": "http://es.slideshare.net/mpazvaleria/etapa-preescolar-15417811", "tu": "https://encrypted-tbn0.gstatic.com/images?q=tbn:ANd9GcRD8Vq7UNe8gJ4McX4ALWunymvz4HloniofN6vbmoA89PbOSD4Q3A", "s": "(3 A 6 A\u00d1OS)ETAPA PREESCOLAR ...", "id": "dLtQMrce3NNORM:"}, "filename": "78.jpg", "image_link": "http://www.esciclismo.com/actualidad/imagenes/g/vuelta_espana_etapa_15_g_2016_unipublic.jpg", "original_filename": "vuelta_espana_etapa_15_g_2016_unipublic.jpg"}, "38": {"success": true, "google": {"ity": "jpg", "tw": 259, "ou": "http://image.slidesharecdn.com/administracionexposicion-130409005935-phpapp01/95/etapa-de-la-direccin-integracin-1-638.jpg?cb=1365469294", "rid": "cp0-wtO7NWCrhM", "sc": 1, "itg": false, "oh": 479, "th": 194, "pt": "Etapa de la Direcci\u00f3n: Integraci\u00f3n", "ow": 638, "isu": "es.slideshare.net", "ru": "http://es.slideshare.net/cinthyaeliizasalcido/etapa-de-la-direccin-integracin", "tu": "https://encrypted-tbn1.gstatic.com/images?q=tbn:ANd9GcQCFo6F4ODaXIs1BSwj5NCXg9MJcP1kTQM5vVOeG1KB_5HACkqzPA", "s": "Etapa de la Direcci\u00f3n: Integraci\u00f3n ...", "id": "5T85Aucohsi83M:"}, "filename": "38.jpg?cb=1417463093", "image_link": "http://image.slidesharecdn.com/etapaproductiva-141201194425-conversion-gate02/95/etapa-productiva-sena-1-638.jpg?cb=1417463093", "original_filename": "etapa-productiva-sena-1-638.jpg?cb=1417463093"}, "06": {"success": true, "google": {"cr": 6, "tw": 364, "th": 138, "ct": 21, "cl": 6, "cb": 21}, "filename": "06.jpg", "image_link": "https://gitanatropical.files.wordpress.com/2013/06/etapas-vida.jpg", "original_filename": "etapas-vida.jpg"}, "64": {"success": true, "google": {"ity": "jpg", "tw": 272, "ou": "http://www.esciclismo.com/actualidad/imagenes/G/tour_de_francia_2013_et16_g.jpg", "rid": "8x0u8ci5MysnfM", "sc": 1, "itg": false, "oh": 425, "th": 185, "pt": "Etapas del Tour de Francia 2013", "ow": 624, "isu": "esciclismo.com", "ru": "http://www.esciclismo.com/especiales/tour_de_francia/2013/etapas.asp", "tu": "https://encrypted-tbn3.gstatic.com/images?q=tbn:ANd9GcS3nX0zedZ5kA2hsNtNE8gWWGXj9xxcVTN05rZtQ0bWN98MGpiugg", "s": "19\u00aa etapa - 19 de julio: Bourg-d\u00b4Oisans - Le Grand-Bornand / 204 Km.", "id": "b9AHe-QLzLdBFM:"}, "filename": "64.png", "image_link": "https://www.colegioetapa.com.br/home/assets//images/colegio_etapa_logo.png", "original_filename": "colegio_etapa_logo.png"}, "16": {"success": true, "google": {"ct": 3, "cb": 9, "tw": 181, "th": 181}, "filename": "16.jpg?cb=1365469294", "image_link": "http://image.slidesharecdn.com/administracionexposicion-130409005935-phpapp01/95/etapa-de-la-direccin-integracin-1-638.jpg?cb=1365469294", "original_filename": "etapa-de-la-direccin-integracin-1-638.jpg?cb=1365469294"}, "30": {"success": true, "google": {"isu": "controlsw.site88.net", "cb": 6, "ou": "http://psidesarrollo2equipo7.wikispaces.com/file/view/Etapas-de-desarrollo-de-Erikson.png/190583404/Etapas-de-desarrollo-de-Erikson.png", "rid": "PmZTMDnQy2ue7M", "s": "etapa 5 identidad frente a confusion de papeles - www.controlsw.site88.net", "ity": "png", "pt": "etapa 5 identidad frente a confusion de papeles - www.controlsw ...", "itg": false, "cl": 6, "th": 198, "oh": 248, "sc": 1, "ow": 320, "cr": 3, "ru": "http://www.controlsw.site88.net/9484/etapa-5-identidad-frente-a-confusion-de-papeles.html", "tu": "https://encrypted-tbn0.gstatic.com/images?q=tbn:ANd9GcRvdxDLtS82J5GLabolSdjF5mGD1lSe1ALqQkypKc_j4kXgL-bm", "ct": 3, "tw": 255, "id": "4AUErwjkGET1CM:"}, "filename": "30.jpg", "image_link": "http://www.esciclismo.com/actualidad/imagenes/g/vuelta_espana_etapa15_g_2012_unipublic.jpg", "original_filename": "vuelta_espana_etapa15_g_2012_unipublic.jpg"}, "36": {"success": true, "google": {"ity": "png", "tw": 120, "ou": "https://www.etapa.com.br/grupoetapa/assets//images/colegio-etapa-logo.png", "rid": "U6bfgzOERV77_M", "sc": 1, "itg": false, "oh": 53, "th": 47, "pt": "ETAPA | Grupo ETAPA Educacional", "ow": 133, "isu": "etapa.com.br", "ru": "https://www.etapa.com.br/en", "tu": "https://encrypted-tbn2.gstatic.com/images?q=tbn:ANd9GcQ5o3hQq0Bh2sVzBrIvQLHNliADN8sYStbXUl8xle4V6Wo9rkyIDw", "s": "Both the strong performance of our high school students on college admission tests and their outstanding academic achievements show the enormous importance ...", "id": "x08eESqjY_CRDM:"}, "filename": "36.jpg?cb=1358025197", "image_link": "http://image.slidesharecdn.com/etapaflica-130112211236-phpapp02/95/etapa-flica-3-638.jpg?cb=1358025197", "original_filename": "etapa-flica-3-638.jpg?cb=1358025197"}, "03": {"success": true, "google": {"tw": 299, "th": 169}, "filename": "03.png", "image_link": "https://www.etapa.com.br/ambienteinspirador/assets//images/home/logotipo.png", "original_filename": "logotipo.png"}, "76": {"success": true, "google": {"ity": "jpg", "ou": "http://2.bp.blogspot.com/-S3Yr7irVXOQ/T10c1GDwR3I/AAAAAAAABaM/lwYpaVwZj6o/s1600/cambio.jpg", "rid": "PEuq1jlNDuCgMM", "th": 171, "itg": false, "oh": 427, "tw": 294, "pt": "Mi peque\u00f1o rinc\u00f3n: Comenzando una nueva etapa", "ow": 734, "isu": "lunnaris81.blogspot.com", "ru": "http://lunnaris81.blogspot.com/2015/11/comenzando-una-nueva-etapa.html", "tu": "https://encrypted-tbn1.gstatic.com/images?q=tbn:ANd9GcRX5kJirn9zBZF5Css7hB3fKkLcJvVf_7tYl2ZuZY1esSzAX6WW", "s": "Besitos, os seguir\u00e9 contando c\u00f3mo evoluciona todo. ;)", "id": "mswBXFXi3uARkM:"}, "filename": "76.jpg", "image_link": "http://cvc.cervantes.es/img/camino_santiago/etapa1_portada.jpg", "original_filename": "etapa1_portada.jpg"}, "08": {"success": true, "google": {"tw": 287, "th": 176}, "filename": "08.png", "image_link": "http://psidesarrollo2equipo7.wikispaces.com/file/view/Etapas-de-desarrollo-de-Erikson.png/190583404/Etapas-de-desarrollo-de-Erikson.png", "original_filename": "Etapas-de-desarrollo-de-Erikson.png"}, "71": {"success": true, "google": {"isu": "etapa.net.ec", "cb": 21, "ou": "http://www.etapa.net.ec/Portals/0/OpenContent/Files/2195/BANNER%20CDMA%20EN%20CAPAS-11.png", "rid": "1w3hVstbhYp5iM", "s": "ETAPA EP - Servicios de Telefon\u00eda, Televisi\u00f3n, Internet, Agua Potable, Alcantarillado de Cuenca - Ecuador &gt; Inicio", "ity": "png", "pt": "ETAPA EP - Servicios de Telefon\u00eda, Televisi\u00f3n, Internet, Agua ...", "itg": false, "cl": 21, "th": 149, "oh": 431, "sc": 1, "ow": 980, "cr": 18, "ru": "http://www.etapa.net.ec/", "tu": "https://encrypted-tbn2.gstatic.com/images?q=tbn:ANd9GcQdfFMaXqgicLlt9K8uixJqesv1Ylqxxyr6HUVzr7Obdfw-J7Y5Yw", "ct": 12, "tw": 339, "id": "NNNSvk82WX1xJM:"}, "filename": "71.jpg?cb=1390821867", "image_link": "http://image.slidesharecdn.com/etapaoral-140127111347-phpapp02/95/etapa-oral-1-638.jpg?cb=1390821867", "original_filename": "etapa-oral-1-638.jpg?cb=1390821867"}, "72": {"success": true, "google": {"ity": "jpg", "tw": 259, "ou": "http://image.slidesharecdn.com/etapaspsicosexualesdesarrollohumano-130602220532-phpapp01/95/etapas-psicosexuales-del-desarrollo-humano-6-638.jpg?cb=1370210789", "rid": "bZqbm7Nf-LO87M", "sc": 1, "itg": false, "oh": 479, "th": 194, "pt": "ETAPAS PSICOSEXUALES DEL DESARROLLO HUMANO", "ow": 638, "isu": "es.slideshare.net", "ru": "http://es.slideshare.net/ireneocasavilcadelacruz7/etapas-psicosexuales-del-desarrollo-humano", "tu": "https://encrypted-tbn3.gstatic.com/images?q=tbn:ANd9GcQoovWxVQuw0r-cVcR6dwNQLwPQnKrqtoHfycwO8b-fty9X0GDgWw", "s": "ETAPA LATENCIA (6 \u2013 11 a\u00f1os)\u00bfQu\u00e9 pasa si no desarrolla adecuadamente?\u00bfQu\u00e9 pasa si no desarrolla adecuadamente?Se limitan la creatividad, la seguridad, ...", "id": "0oAfqtQTewZjPM:"}, "filename": "72.jpg", "image_link": "https://estudiandotusistemadigestivo.files.wordpress.com/2012/06/10919222.jpg", "original_filename": "10919222.jpg"}, "58": {"success": true, "google": {"isu": "es.slideshare.net", "oh": 479, "tw": 259, "ou": "http://image.slidesharecdn.com/etapaflica-130112211236-phpapp02/95/etapa-flica-3-638.jpg?cb=1358025197", "rid": "atSFSSVd2OATIM", "ity": "jpg", "itg": false, "cl": 6, "th": 194, "pt": "Etapa f\u00e1lica", "ow": 638, "cr": 12, "ru": "http://es.slideshare.net/ariannacanedo/etapa-flica", "tu": "https://encrypted-tbn1.gstatic.com/images?q=tbn:ANd9GcSGOn7vhrv03dHGpDWyKsqViaBpWSYczi6al4O7aOKjDCaMHNLJ3g", "s": "Complejo de EdipoSe refiere a la atracci\u00f3n sexual que el ni\u00f1o tiende asentir por su madre durante la etapa f\u00e1lica. Al mismotiempo ve a su padre como un ...", "id": "nMPdC5QvBS7RyM:"}, "filename": "58.jpg", "image_link": "http://www.universobebes.com/wp-content/uploads/etapas-del-desarrollo-infantil.jpg", "original_filename": "etapas-del-desarrollo-infantil.jpg"}, "80": {"success": true, "google": {"ity": "jpg", "cb": 18, "ou": "http://www.universobebes.com/wp-content/uploads/etapas-del-desarrollo-infantil.jpg", "rid": "LBpZMHLKdPxyHM", "s": "", "sc": 1, "itg": false, "oh": 337, "th": 183, "pt": "Etapas del desarrollo infantil", "ow": 506, "isu": "universobebes.com", "ru": "http://www.universobebes.com/etapas-del-desarrollo-infantil/", "tu": "https://encrypted-tbn0.gstatic.com/images?q=tbn:ANd9GcS6Px2plZbKRR3iMi7k1Ax9vbS7RX8JF-wn8fASpORyIniLSSLJeg", "ct": 21, "tw": 275, "id": "ahJc7VCln6n48M:"}, "filename": "80.jpg", "image_link": "http://www.esciclismo.com/actualidad/imagenes/g/tour_de_francia_2016_et09_g.jpg", "original_filename": "tour_de_francia_2016_et09_g.jpg"}, "55": {"success": true, "google": {"ity": "png", "tw": 217, "ou": "http://s3-eu-west-1.amazonaws.com/rankia/blog/upload/images/blogs/secretosbolsa/Bolsa-etapas.png", "rid": "rQbumOfbXfP4tM", "sc": 1, "itg": false, "oh": 401, "th": 233, "pt": "Las etapas del m\u00e9todo Weinstein", "ow": 373, "isu": "megabolsa.com", "ru": "http://www.megabolsa.com/2015/07/30/las-etapas-del-metodo-weinstein/", "tu": "https://encrypted-tbn1.gstatic.com/images?q=tbn:ANd9GcQ1x6BFcxX_5LJ0_Temf9LaB2_Y0TWC_miwHdcKF9EjK5ub_Gc8fA", "s": "ETAPAS DEL MERCADO SEG\u00daN STAN WEINSTEIN", "id": "tr-pafPyahqHPM:"}, "filename": "55.png", "image_link": "http://www.etapa.net.ec/Portals/0/OpenContent/Files/2195/BANNER CDMA EN CAPAS-10.png", "original_filename": "BANNER CDMA EN CAPAS-10.png"}, "33": {"success": true, "google": {"ity": "png", "tw": 206, "ou": "http://cadenaradialvision.com/wp-content/uploads/2015/10/ETAPA-EP.png", "rid": "fFILA-jDLX-z7M", "sc": 1, "itg": false, "oh": 162, "th": 129, "pt": "Cadena Radial Visi\u00f3n \u00bb ETAPA EP ENTREGA OBRAS EN YANATURO DE LA ...", "ow": 258, "isu": "cadenaradialvision.com", "ru": "http://cadenaradialvision.com/2016/01/25/etapa-ep-entrega-obras-en-yanaturo-de-la-parroquia-sinincay/", "tu": "https://encrypted-tbn0.gstatic.com/images?q=tbn:ANd9GcQjwcEaY4Rf2ZETMqLdVQDo2IOA7wqXVVdIeURIKIOAFki_9Oha", "s": "La Municipalidad de Cuenca y su Empresa ETAPA EP entreg\u00f3 este fin de semana los trabajos de alcantarillado combinado y obras complementarias en el sector de ...", "id": "QgdMNFQZv-TkzM:"}, "filename": "33.png", "image_link": "http://s3-eu-west-1.amazonaws.com/rankia/blog/upload/images/blogs/secretosbolsa/Bolsa-etapas.png", "original_filename": "Bolsa-etapas.png"}, "60": {"success": true, "google": {"ity": "jpg", "tw": 197, "ou": "http://image.slidesharecdn.com/etapaproductiva-141201194425-conversion-gate02/95/etapa-productiva-sena-1-638.jpg?cb=1417463093", "rid": "W7ZE0g9NIlQzfM", "sc": 1, "itg": false, "oh": 826, "th": 256, "pt": "Etapa productiva SENA", "ow": 638, "isu": "es.slideshare.net", "ru": "http://es.slideshare.net/manueldejesussotocardenas/etapa-productiva-sena", "tu": "https://encrypted-tbn1.gstatic.com/images?q=tbn:ANd9GcQtKXYnVfwmYErMqwF-r1-M4Bhhn-Gs3IbQbumezWHHIr9Z6j3hYw", "s": "Mi etapa Servicio Nacional de Aprendizaje - SENA 2014 Z o n a C a r i b e  Z o n a A ...", "id": "CXXt8u9F0AXaxM:"}, "filename": "60.jpg", "image_link": "https://pbs.twimg.com/profile_images/697898219607556097/PNA2UtTl.jpg", "original_filename": "PNA2UtTl.jpg"}, "65": {"success": true, "google": {"isu": "youtube.com", "cb": 9, "ou": "https://i.ytimg.com/vi/aG4FB__Ao2k/maxresdefault.jpg", "rid": "IU3Itsjr11X3RM", "s": "Dieta en etapa de definicion... sorprendete!", "ity": "jpg", "pt": "Dieta en etapa de definicion... sorprendete! - YouTube", "itg": false, "cl": 6, "th": 225, "oh": 1920, "sc": 1, "ow": 1920, "cr": 9, "ru": "https://www.youtube.com/watch?v=aG4FB__Ao2k", "tu": "https://encrypted-tbn2.gstatic.com/images?q=tbn:ANd9GcRFOSDfd-FBRrneb7Yr4ecIDRPAibORZSAQ_dLZXfhQC88mppwAWg", "ct": 3, "tw": 225, "id": "1Z42OT_kHVXAFM:"}, "filename": "65.jpg?cb=1411413252", "image_link": "http://image.slidesharecdn.com/etapasdeldesarrollopsicosexual-140823092316-phpapp02/95/etapas-del-desarrollo-psicosexual-de-sigmund-freud-15-638.jpg?cb=1411413252", "original_filename": "etapas-del-desarrollo-psicosexual-de-sigmund-freud-15-638.jpg?cb=1411413252"}, "83": {"success": true, "google": {"isu": "congressosaber.com.br", "cb": 9, "ou": "http://www.congressosaber.com.br/userfiles/image/Feira%202013/logo%20Sistema%20com%20volume.jpg", "rid": "fhftn2nmoT9aUM", "s": "O Etapa \u00e9 um dos mais importantes grupos educacionais do pa\u00eds. Com a diretriz de proporcionar ensino da mais alta qualidade, desde a educa\u00e7\u00e3o b\u00e1sica at\u00e9 o ...", "ity": "jpg", "pt": "Congresso e Feira Saber 2013", "itg": false, "cl": 6, "th": 201, "oh": 1320, "sc": 1, "ow": 1642, "cr": 9, "ru": "http://www.congressosaber.com.br/index.php?acao=57", "tu": "https://encrypted-tbn0.gstatic.com/images?q=tbn:ANd9GcTKp52AIHr4BWHici466_9WtB1XPPEBUE8ohiW7i7Cf2DdAg-jQ", "ct": 9, "tw": 250, "id": "EEeUgl0In0JHjM:"}, "filename": "83.png?w=1180&h=435&crop=1", "image_link": "https://fideba.files.wordpress.com/2015/02/fideba-3-etapa-01.png?w=1180&h=435&crop=1", "original_filename": "fideba-3-etapa-01.png?w=1180&h=435&crop=1"}, "43": {"success": true, "google": {"isu": "twitter.com", "cb": 21, "ou": "https://pbs.twimg.com/profile_images/651830579495837697/HNHZbb8m.jpg", "rid": "FERzWyn_Ym8tjM", "s": "", "ity": "jpg", "pt": "Curso ETAPA (@cursoetapa) | Twitter", "itg": false, "cl": 6, "th": 225, "oh": 512, "sc": 1, "ow": 512, "cr": 3, "ru": "https://twitter.com/cursoetapa", "tu": "https://encrypted-tbn3.gstatic.com/images?q=tbn:ANd9GcQH9-8GX8AcJ4f7L6xR4Vi6bU9vd8J-vYKpJc_b0bRIQr_FMZPU", "ct": 21, "tw": 225, "id": "mc472VltzBc2bM:"}, "filename": "43.jpg", "image_link": "https://i.ytimg.com/vi/aG4FB__Ao2k/maxresdefault.jpg", "original_filename": "maxresdefault.jpg"}, "90": {"success": true, "google": {"ity": "jpg", "tw": 259, "ou": "http://image.slidesharecdn.com/etapasdellenguaje-131206152836-phpapp02/95/etapas-del-lenguaje-0-5-aos-7-638.jpg?cb=1386343768", "rid": "5BoaYzWLYqaoVM", "sc": 1, "itg": false, "oh": 479, "th": 194, "pt": "Etapas del lenguaje 0 - 5 a\u00f1os", "ow": 638, "isu": "es.slideshare.net", "ru": "http://es.slideshare.net/ClaudiaPanda/etapas-del-lenguaje-0-5-aos", "tu": "https://encrypted-tbn0.gstatic.com/images?q=tbn:ANd9GcQ5FVqBS-MtWy_OGHILPwCXCoNS_-nIp1qdhfTEMRBBAmrf2soC", "s": "7. Etapa Ling\u00fc\u00edstica ...", "id": "YIWgEAPl3uMckM:"}, "filename": "90.png", "image_link": "http://img.irtve.es/css/rtve.deportes/rtve.deportes.ciclismo/vuelta-espana/2015/perfiles/etapa_02.png", "original_filename": "etapa_02.png"}, "61": {"success": true, "google": {"ity": "jpg", "cb": 9, "ou": "http://www.monografias.com/trabajos102/desarrollo-psicosexual-infancia/image006.jpg", "rid": "m-v7MfJBuOEreM", "s": "ETAPA LATENTE", "th": 209, "itg": false, "oh": 277, "tw": 241, "pt": "Desarrollo psicosexual de la infancia - Monografias.com", "ow": 318, "isu": "monografias.com", "ru": "http://www.monografias.com/trabajos102/desarrollo-psicosexual-infancia/desarrollo-psicosexual-infancia.shtml", "tu": "https://encrypted-tbn3.gstatic.com/images?q=tbn:ANd9GcQahfOuHoOnq75biIlKy1yO9-Tw1YsJZJ4ktkr8-dsbFvQnqZY4", "ct": 3, "id": "YWx767-8ONKc6M:"}, "filename": "61.jpg", "image_link": "http://www.congressosaber.com.br/userfiles/image/Feira 2013/logo Sistema com volume.jpg", "original_filename": "logo Sistema com volume.jpg"}, "24": {"success": true, "google": {"ity": "png", "tw": 298, "ou": "http://correvedile.com/images/danielgarcia/etapas-vida.png", "rid": "NSegJqSreqhKAM", "sc": 1, "itg": false, "oh": 276, "th": 169, "pt": "Un cuento que explica cada etapa de la vida y la raz\u00f3n de ella ...", "ow": 487, "isu": "correvedile.com", "ru": "http://correvedile.com/danielgarcia/cuento-curioso", "tu": "https://encrypted-tbn2.gstatic.com/images?q=tbn:ANd9GcQ5fJFtNotYf7t8cmhLgDq1aK1Asil482bYAzvEAWxBR7Ealp0A", "s": "El que viene a continuaci\u00f3n es una interesante f\u00f3rmula de cuento que es a la vez chiste, f\u00e1bula, par\u00e1bola y rega\u00f1o para ense\u00f1ar (matem\u00e1ticas, moral, ...", "id": "gspKJA3CmAdcKM:"}, "filename": "24.jpg", "image_link": "https://www.colegioetapa.com.br/home/assets//images/backgrounds/1920/bolsascolegio/2015_1/inscreva_se.jpg", "original_filename": "inscreva_se.jpg"}, "26": {"success": true, "google": {"isu": "emprenden.net", "oh": 300, "tw": 225, "ou": "http://www.emprenden.net/wp-content/uploads/2009/09/steps1-300x300.jpg", "rid": "mtmr445NWibkUM", "s": "Existen pasos que se tienen que dar para poder emprender, seg\u00fan Eduardo Kastika podemos encontrar tres etapas.", "ity": "jpg", "itg": false, "cl": 9, "th": 225, "pt": "Las etapas para emprender | Emprenden", "sc": 1, "ow": 300, "cr": 12, "ru": "http://www.emprenden.net/las-etapas-para-emprender/", "tu": "https://encrypted-tbn1.gstatic.com/images?q=tbn:ANd9GcTSThFglw23WbZ7smFM6ceRr4gGCKhpTB0SFafKmvUDdaI5bjKc", "ct": 3, "id": "nrzlaakkxw8U_M:"}, "filename": "26.jpg?cb=1277220615", "image_link": "http://image.slidesharecdn.com/6a11aos-100622151613-phpapp02/95/etapa-escolar-1-728.jpg?cb=1277220615", "original_filename": "etapa-escolar-1-728.jpg?cb=1277220615"}, "35": {"success": true, "google": {"isu": "etapa.net.ec", "cb": 15, "ou": "http://www.etapa.net.ec/Portals/0/logoMainNew.png", "rid": "1w3hVstbhYp5iM", "s": "ETAPA EP - Servicios de Telefon\u00eda, Televisi\u00f3n, Internet, Agua Potable, Alcantarillado de", "ity": "png", "pt": "ETAPA EP - Servicios de Telefon\u00eda, Televisi\u00f3n, Internet, Agua ...", "itg": false, "cl": 3, "th": 60, "oh": 75, "sc": 1, "ow": 350, "cr": 3, "ru": "http://www.etapa.net.ec/", "tu": "https://encrypted-tbn0.gstatic.com/images?q=tbn:ANd9GcQW5y7KUMWAJakRoq9RdpZQYCZ6zqd0hRV_giddWUdruFMumFa2", "ct": 6, "tw": 280, "id": "5cHEFrezlnoBHM:"}, "filename": "35.jpg", "image_link": "http://www.newclick.es/imagenes/etapas-del-diseno-de-una-pagina-web.jpg", "original_filename": "etapas-del-diseno-de-una-pagina-web.jpg"}}